quanestimation/Manifest.toml
quanestimation/Project.toml
quanestimation/__init__.py
quanestimation/AdaptiveScheme/Adapt.py
quanestimation/AdaptiveScheme/Adapt_MZI.py
quanestimation/AdaptiveScheme/__init__.py
quanestimation/AsymptoticBound/AnalogCramerRao.py
quanestimation/AsymptoticBound/CramerRao.py
quanestimation/AsymptoticBound/__init__.py
quanestimation/BayesianBound/BayesCramerRao.py
quanestimation/BayesianBound/BayesEstimation.py
quanestimation/BayesianBound/ZivZakai.py
quanestimation/BayesianBound/__init__.py
quanestimation/Common/Common.py
quanestimation/Common/__init__.py
quanestimation/Common/_julia_project.py
quanestimation/Common/utils.jl
quanestimation/ComprehensiveOpt/AD_Compopt.py
quanestimation/ComprehensiveOpt/ComprehensiveStruct.py
quanestimation/ComprehensiveOpt/DE_Compopt.py
quanestimation/ComprehensiveOpt/PSO_Compopt.py
quanestimation/ComprehensiveOpt/__init__.py
quanestimation/ControlOpt/ControlStruct.py
quanestimation/ControlOpt/DDPG_Copt.py
quanestimation/ControlOpt/DE_Copt.py
quanestimation/ControlOpt/GRAPE_Copt.py
quanestimation/ControlOpt/PSO_Copt.py
quanestimation/ControlOpt/__init__.py
quanestimation/MeasurementOpt/AD_Mopt.py
quanestimation/MeasurementOpt/DE_Mopt.py
quanestimation/MeasurementOpt/MeasurementStruct.py
quanestimation/MeasurementOpt/PSO_Mopt.py
quanestimation/MeasurementOpt/__init__.py
quanestimation/Parameterization/GeneralDynamics.py
quanestimation/Parameterization/NonDynamics.py
quanestimation/Parameterization/__init__.py
quanestimation/Resource/Resource.py
quanestimation/Resource/__init__.py
quanestimation/StateOpt/AD_Sopt.py
quanestimation/StateOpt/DDPG_Sopt.py
quanestimation/StateOpt/DE_Sopt.py
quanestimation/StateOpt/NM_Sopt.py
quanestimation/StateOpt/PSO_Sopt.py
quanestimation/StateOpt/RI_Sopt.py
quanestimation/StateOpt/StateStruct.py
quanestimation/StateOpt/__init__.py
quanestimation/examples/Julia examples/Bayesian_CramerRao_bounds.jl
quanestimation/examples/Julia examples/Bayesian_estimation.jl
quanestimation-0.2.8.dist-info/licenses/AUTHORS.rst
quanestimation-0.2.8.dist-info/licenses/LICENSE
quanestimation-0.2.8.dist-info/METADATA
quanestimation-0.2.8.dist-info/WHEEL
quanestimation-0.2.8.dist-info/entry_points.txt
quanestimation-0.2.8.dist-info/top_level.txt
quanestimation-0.2.8.dist-info/RECORD
