Metadata-Version: 2.4
Name: quanestimation
Version: 0.2.8
Summary: A package for quantum parameter estimation.
Home-page: https://github.com/QuanEstimation/QuanEstimation
Author: Jing Liu et al.
Author-email: "QuanEstimation Group (Jing Liu et al.)" <liujing@hainanu.edu.cn>
License: BSD 3-Clause License
Project-URL: Homepage, https://github.com/QuanEstimation/QuanEstimation
Keywords: quanestimation
Classifier: Development Status :: 3 - Alpha
Classifier: Intended Audience :: Developers
Classifier: License :: OSI Approved :: BSD License
Classifier: Natural Language :: English
Classifier: Programming Language :: Python :: 3
Classifier: Programming Language :: Python :: 3.10
Classifier: Programming Language :: Python :: 3.11
Classifier: Programming Language :: Python :: 3.12
Classifier: Programming Language :: Python :: 3.13
Requires-Python: >=3.10
License-File: LICENSE
License-File: AUTHORS.rst
Requires-Dist: pip>=19.2.3
Requires-Dist: bump2version>=0.5.11
Requires-Dist: wheel>=0.33.6
Requires-Dist: numpy
Requires-Dist: sympy
Requires-Dist: scipy
Requires-Dist: cvxpy
Requires-Dist: juliacall>=0.9.26
Requires-Dist: more_itertools
Requires-Dist: julia_project
Requires-Dist: h5py
Provides-Extra: test
Requires-Dist: pytest; extra == "test"
Requires-Dist: coverage; extra == "test"
Requires-Dist: codecov; extra == "test"
Provides-Extra: dev
Requires-Dist: bump2version>=0.5.11; extra == "dev"
Requires-Dist: wheel>=0.33.6; extra == "dev"
Requires-Dist: build; extra == "dev"
Requires-Dist: pytest; extra == "dev"
Requires-Dist: coverage; extra == "dev"
Requires-Dist: codecov; extra == "dev"
Provides-Extra: docs
Requires-Dist: mkdocs; extra == "docs"
Requires-Dist: mkdocs-material; extra == "docs"
Requires-Dist: mkdocstrings[python]; extra == "docs"
Dynamic: author
Dynamic: home-page
Dynamic: license-file
Dynamic: requires-python
